datamonk/scriptorium/__init__.py
datamonk/scriptorium/apps/__init__.py
datamonk/scriptorium/apps/adform.py
datamonk/scriptorium/apps/clockify.py
datamonk/scriptorium/apps/dataform.py
datamonk/scriptorium/apps/ecomail.py
datamonk/scriptorium/apps/fakturoid.py
datamonk/scriptorium/apps/fio.py
datamonk/scriptorium/apps/googleAnalytics.py
datamonk/scriptorium/apps/googleSheets.py
datamonk/scriptorium/apps/heureka.py
datamonk/scriptorium/apps/heureka_old.py
datamonk/scriptorium/apps/instagram.py
datamonk/scriptorium/apps/slack.py
datamonk/scriptorium/apps/sql_database.py
datamonk/scriptorium/apps/teamwork.py
datamonk/scriptorium/apps/toggl.py
datamonk/scriptorium/process/__init__.py
datamonk/scriptorium/process/monitoring.py
datamonk/scriptorium/storage/__init__.py
datamonk/scriptorium/storage/gcp.py
datamonk/scriptorium/storage/local.py
datamonk/scriptorium/transformations/__init__.py
datamonk/scriptorium/transformations/XMLtoCSV.py
datamonk_scriptorium-0.5.7.dist-info/WHEEL
datamonk_scriptorium-0.5.7.dist-info/METADATA
datamonk_scriptorium-0.5.7.dist-info/RECORD
