Metadata-Version: 2.1
Name: datamonk-scriptorium
Version: 0.5.7
Summary: 
Author: Vit Mrnavek
Author-email: vit.mrnavek@datamonk.cz
Requires-Python: >=3.9.0,<3.10.0
Classifier: Programming Language :: Python :: 3
Classifier: Programming Language :: Python :: 3.9
Requires-Dist: SQLAlchemy (>=1.4.7,<2.0.0)
Requires-Dist: datamonk-utils (>=0.1.3,<0.2.0)
Requires-Dist: google-api-python-client (>=2.0.2,<3.0.0)
Requires-Dist: google-auth (>=2.0.0,<3.0.0)
Requires-Dist: google-auth-oauthlib (>=0.4.3,<0.5.0)
Requires-Dist: google-cloud-bigquery (>=2.13.1,<3.0.0)
Requires-Dist: google-cloud-bigquery-storage (>=2.3.0,<3.0.0)
Requires-Dist: google-cloud-storage (>=1.37.0,<2.0.0)
Requires-Dist: numpy (>=1.20.1,<2.0.0)
Requires-Dist: oauth2client (>=4.1.3,<5.0.0)
Requires-Dist: pandas (>=1.2.3,<2.0.0)
Requires-Dist: pandasql (>=0.7.3,<1.0.0)
Requires-Dist: pyarrow (>=3.0.0,<4.0.0)
Requires-Dist: pygsheets (>=2.0.5,<3.0.0)
Requires-Dist: pymssql (>=2.2.0,<3.0.0)
Requires-Dist: retrying (>=1.3.3,<2.0.0)
Requires-Dist: setuptools (>=54.2.0,<55.0.0)
Requires-Dist: slack-sdk (>=3.18.0,<4.0.0)
